pd_aws_lambda/__init__.py
pd_aws_lambda/dispatcher.py
pd_aws_lambda/handlers/__init__.py
pd_aws_lambda/handlers/logger.py
pd_aws_lambda/handlers/shell.py
pd_aws_lambda/handlers/wsgi.py
pd_aws_lambda-2.0.0.dist-info/LICENSE
pd_aws_lambda-2.0.0.dist-info/WHEEL
pd_aws_lambda-2.0.0.dist-info/METADATA
pd_aws_lambda-2.0.0.dist-info/RECORD
