Metadata-Version: 2.1
Name: pd-aws-lambda
Version: 2.0.0
Summary: Integrate your python applications with AWS Lambda and https://pythondeploy.co/.
Home-page: https://github.com/pythondeploy/aws-lambda
License: BSD-3-Clause
Author: Federico Jaramillo Martínez
Author-email: federicojaramillom@gmail.com
Requires-Python: >=3.7,<4.0
Classifier: License :: OSI Approved :: BSD License
Classifier: Programming Language :: Python :: 3
Classifier: Programming Language :: Python :: 3.7
Classifier: Programming Language :: Python :: 3.8
Classifier: Programming Language :: Python :: 3.9
Requires-Dist: apig-wsgi (>=2.0.0)
